{
	"version": "1.0.0",
	"commandPath": "service/itxpt/v2/avms/command/login/duty",
	"monitoredRunState": {
		"recordedAtTime": "2017-07-16T11:43:27",
		"monitoredBlockRef": "9301",
		"currentRunInfo": {
			"runState": "RunToPattern",
			"patternRunType": "JourneyPattern",
			"journeyPatternRef": "9308",
			"vehicleJourneyRef": "930110",
			"verifiedRunState": true,
		},
		"nextRunInfo": {
			"runState": "RunToPattern",
			"patternRunType": "JourneyPattern",
			"journeyPatternRef": "9311",
			"vehicleJourneyRef": "930111"
		}
	}
}